AUTHORS.rst
MANIFEST.in
README.rst
setup.py
wkhtmltopdf/.DS_Store
wkhtmltopdf/__init__.py
wkhtmltopdf/api.py
wkhtmltopdf/api.pyc
wkhtmltopdf/main.py
wkhtmltopdf/main.pyc
wkhtmltopdf/tests.py
wkhtmltopdf.egg-info/PKG-INFO
wkhtmltopdf.egg-info/SOURCES.txt
wkhtmltopdf.egg-info/dependency_links.txt
wkhtmltopdf.egg-info/top_level.txt