Metadata-Version: 1.0
Name: wkhtmltopdf
Version: 0.2
Summary: Simple python wrapper for wkhtmltopdf
Home-page: http://github.com/qoda/python-wkhtmltopdf
Author: Qoda
Author-email: jpbydendyk@gmail.com
License: BSD
Platform: UNKNOWN
Classifier: Programming Language :: Python
Classifier: License :: OSI Approved :: BSD License
Classifier: Development Status :: 4 - Beta
Classifier: Operating System :: OS Independent
Classifier: Intended Audience :: Developers
Classifier: Topic :: Internet :: WWW/HTTP :: Dynamic Content
